{
  "__file": "wp_block",
  "title": "Documents",
  "content": "<!-- wp:greenshift-blocks/element {\"id\":\"gsbp-c6336a3\",\"tag\":\"section\",\"type\":\"inner\",\"localId\":\"gsbp-c6336a3\",\"align\":\"full\",\"dynamicAttributes\":[{\"name\":\"data-type\",\"value\":\"section-component\"}],\"styleAttributes\":{\"display\":[\"flex\"],\"justifyContent\":[\"center\"],\"flexDirection\":[\"column\"],\"alignItems\":[\"center\"],\"paddingRight\":[\"var(\\u002d\\u002dwp\\u002d\\u002dcustom\\u002d\\u002dspacing\\u002d\\u002dside, min(3vw, 20px))\"],\"paddingLeft\":[\"var(\\u002d\\u002dwp\\u002d\\u002dcustom\\u002d\\u002dspacing\\u002d\\u002dside, min(3vw, 20px))\"],\"paddingTop\":[\"var(\\u002d\\u002dwp\\u002d\\u002dcustom\\u002d\\u002dspacing\\u002d\\u002dtop, 0px)\"],\"paddingBottom\":[\"var(\\u002d\\u002dwp\\u002d\\u002dcustom\\u002d\\u002dspacing\\u002d\\u002dbottom, 0px)\"],\"marginTop\":[\"0px\"],\"marginBottom\":[\"0px\"],\"paddingLink_Extra\":\"lr\",\"position\":[\"relative\"],\"backgroundColor\":[\"var(\\u002d\\u002dwp\\u002d\\u002dpreset\\u002d\\u002dcolor\\u002d\\u002dcard-border, #f0f0f0)\"]},\"isVariation\":\"contentwrapper\"} -->\n<section class=\"gsbp-c6336a3 alignfull\" data-type=\"section-component\"><!-- wp:greenshift-blocks/element {\"id\":\"gsbp-edbf021\",\"type\":\"inner\",\"localId\":\"gsbp-edbf021\",\"styleAttributes\":{\"marginTop\":[\"48px\"],\"marginBottom\":[\"48px\"],\"marginLeft\":[\"0px\"],\"marginRight\":[\"0px\"],\"paddingLink_Extra\":\"all\",\"paddingTop\":[\"0px\"],\"paddingBottom\":[\"0px\"],\"paddingLeft\":[\"0px\"],\"paddingRight\":[\"0px\"],\"marginLink_Extra\":\"tb\"}} -->\n<div class=\"gsbp-edbf021\"><!-- wp:greenshift-blocks/element {\"id\":\"gsbp-7555071\",\"textContent\":\"ឯកសារ\",\"tag\":\"h2\",\"localId\":\"gsbp-7555071\",\"styleAttributes\":{\"marginLink_Extra\":\"all\",\"marginTop\":[\"0\"],\"marginBottom\":[\"0\"],\"marginLeft\":[\"0\"],\"marginRight\":[\"0\"]}} -->\n<h2 class=\"gsbp-7555071\">ឯកសារ</h2>\n<!-- /wp:greenshift-blocks/element --></div>\n<!-- /wp:greenshift-blocks/element -->\n\n<!-- wp:greenshift-blocks/element {\"id\":\"gsbp-91867cc\",\"metadata\":{\"name\":\"Content Area\"},\"type\":\"inner\",\"localId\":\"gsbp-91867cc\",\"dynamicAttributes\":[{\"name\":\"data-type\",\"value\":\"content-area-component\"}],\"styleAttributes\":{\"maxWidth\":[\"100%\"],\"width\":[\"var(\\u002d\\u002dwp\\u002d\\u002dstyle\\u002d\\u002dglobal\\u002d\\u002dwide-size, 1200px)\"],\"backgroundColor\":[\"var(\\u002d\\u002dwp\\u002d\\u002dpreset\\u002d\\u002dcolor\\u002d\\u002dcontrastcolor, #fffffe)\"],\"marginTop\":[\"\"],\"marginBottom\":[\"48px\"],\"paddingLink_Extra\":\"all\",\"paddingTop\":[\"2rem\"],\"paddingBottom\":[\"2rem\"],\"paddingLeft\":[\"2rem\"],\"paddingRight\":[\"2rem\"],\"borderRadiusLink_Extra\":true,\"borderTopLeftRadius\":[\"7px\"],\"borderBottomLeftRadius\":[\"7px\"],\"borderTopRightRadius\":[\"7px\"],\"borderBottomRightRadius\":[\"7px\"]},\"isVariation\":\"nocolumncontent\"} -->\n<div class=\"gsbp-91867cc\" data-type=\"content-area-component\"><!-- wp:greenshift-blocks/querygrid {\"id\":\"gsbp-9640416\",\"cat\":[{\"label\":\"ព័ត៌មានថ្មីៗ\",\"id\":4,\"value\":4},{\"label\":\"សេចក្តីជូនដំណឹង\",\"id\":5,\"value\":5}],\"show\":8,\"enable_pagination\":\"1\",\"filter_enable_pagination\":\"0\",\"displayStyle\":\"custom\"} -->\n<!-- wp:greenshift-blocks/element {\"id\":\"gsbp-22798b7\",\"type\":\"inner\",\"localId\":\"gsbp-22798b7\",\"styleAttributes\":{\"marginLink_Extra\":\"all\",\"marginTop\":[\"0px\"],\"marginBottom\":[\"0px\"],\"marginLeft\":[\"0px\"],\"marginRight\":[\"0px\"],\"fontSize\":[\"16px\"],\"display\":[\"flex\",\"flex\"],\"flexDirection\":[\"column\"],\"justifyContent\":[\"center\"],\"paddingLink_Extra\":\"tb\",\"paddingTop\":[\"34px\"],\"paddingBottom\":[\"34px\"],\"borderLink_Extra\":true,\"borderBottomWidth\":[\"1px\"],\"borderBottomStyle\":[\"solid\"],\"borderBottomColor\":[\"#cfcfcf\"]}} -->\n<div class=\"gsbp-22798b7\"><!-- wp:greenshift-blocks/element {\"id\":\"gsbp-ec87090\",\"type\":\"inner\",\"localId\":\"gsbp-ec87090\",\"styleAttributes\":{\"display\":[\"flex\"],\"flexDirection\":[\"row\"],\"alignItems\":[\"center\"],\"paddingTop\":[\"0px\"],\"paddingBottom\":[\"12px\"],\"paddingLeft\":[\"0px\"],\"paddingRight\":[\"0px\"]}} -->\n<div class=\"gsbp-ec87090\"><!-- wp:greenshift-blocks/element {\"id\":\"gsbp-165eade\",\"textContent\":\"ឯកសារ៖ \",\"tag\":\"p\",\"localId\":\"gsbp-165eade\",\"styleAttributes\":{\"paddingTop\":[\"0px\"],\"paddingBottom\":[\"0px\"],\"paddingLeft\":[\"0px\"],\"paddingRight\":[\"5px\"],\"marginLink_Extra\":\"all\",\"marginTop\":[\"0px\"],\"marginBottom\":[\"0px\"],\"marginLeft\":[\"0px\"],\"marginRight\":[\"0px\"],\"fontSize\":[null,null,null,\"15px\"]}} -->\n<p class=\"gsbp-165eade\">ឯកសារ៖ </p>\n<!-- /wp:greenshift-blocks/element -->\n\n<!-- wp:greenshift-blocks/meta {\"id\":\"gsbp-f72d138\",\"typographyValue\":{\"textShadow\":[],\"colorlinks\":\"var(\\u002d\\u002dwp\\u002d\\u002dpreset\\u002d\\u002dcolor\\u002d\\u002dtextonbutton, #010101)\",\"size\":[\"16px\",null,null,\"15px\"],\"line_height\":[\"20px\"],\"hoverUnderline\":false,\"colorHover\":\"\",\"colorlinksHover\":\"var(\\u002d\\u002dwp\\u002d\\u002dpreset\\u002d\\u002dcolor\\u002d\\u002dsecondary, #f56c00)\",\"decoration\":\"remove\",\"color\":\"#ffffff00\",\"customweight\":[0],\"customweightnumber\":[300]},\"field\":\"category\",\"post_type\":\"post\",\"type\":\"taxonomylink\",\"typeselect\":\"taxonomy\",\"showtoggle\":false} /--></div>\n<!-- /wp:greenshift-blocks/element -->\n\n<!-- wp:greenshift-blocks/element {\"id\":\"gsbp-785788c\",\"type\":\"inner\",\"localId\":\"gsbp-785788c\",\"styleAttributes\":{\"marginLink_Extra\":\"all\",\"marginTop\":[\"0px\"],\"marginBottom\":[\"0px\"],\"marginLeft\":[\"0px\"],\"marginRight\":[\"0px\"],\"paddingTop\":[\"0px\"],\"paddingBottom\":[\"17px\"],\"paddingLeft\":[\"0px\"],\"paddingRight\":[\"0px\"],\"alignItems\":[\"center\"],\"alignSelf\":[\"center\",\"center\"],\"justifySelf\":[\"center\",\"center\"],\"fontSize\":[null,null,\"\"],\"gridTemplateLink_Extra\":false,\"gridLayoutItems_Extra\":1,\"gridLayout_Extra\":{\"desktop\":{\"layouts\":[{\"w\":4,\"h\":1,\"x\":0,\"y\":0,\"i\":\"0\",\"moved\":false,\"static\":false}],\"cols\":4,\"allowOverlap\":false,\"compactType\":\"horizontal\"},\"tablet\":{\"layouts\":[{\"i\":\"0\",\"x\":0,\"y\":0,\"w\":1,\"h\":1}],\"cols\":2,\"allowOverlap\":false,\"compactType\":\"horizontal\"},\"mobile\":{\"layouts\":[{\"i\":\"0\",\"x\":0,\"y\":0,\"w\":1,\"h\":1}],\"cols\":1,\"allowOverlap\":false,\"compactType\":\"horizontal\"}},\"display\":[\"inline-flex\"],\"flexDirection\":[\"row\",null,\"column\"],\"justifyContent\":[\"flex-start\"],\"width\":[\"100%\"]}} -->\n<div class=\"gsbp-785788c\"><!-- wp:greenshift-blocks/element {\"id\":\"gsbp-30d228b\",\"type\":\"inner\",\"localId\":\"gsbp-30d228b\",\"styleAttributes\":{\"marginRight\":[\"15px\"],\"flexDirection\":[\"row\"],\"alignItems\":[\"center\"],\"width\":[\"80%\"],\"display\":[\"flex\",null,\"flex\"]}} -->\n<div class=\"gsbp-30d228b\"><!-- wp:greenshift-blocks/element {\"id\":\"gsbp-f73cf16\",\"type\":\"inner\",\"localId\":\"gsbp-f73cf16\",\"styleAttributes\":{\"paddingLeft\":[null,null,\"\"]}} -->\n<div class=\"gsbp-f73cf16\"><!-- wp:greenshift-blocks/element {\"id\":\"gsbp-fc703ac\",\"tag\":\"svg\",\"icon\":{\"icon\":{\"font\":\"rhicon rhi-check\",\"svg\":\"\",\"image\":\"\",\"svgRaw\":\"\\u003csvg viewBox=\\u00220 0 384 512\\u0022 fill=\\u0022currentColor\\u0022 xmlns=\\u0022http://www.w3.org/2000/svg\\u0022 aria-hidden=\\u0022true\\u0022\\u003e\\u003cpath d=\\u0022M181.9 256.1c-5-16-4.9-46.9-2-46.9 8.4 0 7.6 36.9 2 46.9zm-1.7 47.2c-7.7 20.2-17.3 43.3-28.4 62.7 18.3-7 39-17.2 62.9-21.9-12.7-9.6-24.9-23.4-34.5-40.8zM86.1 428.1c0 .8 13.2-5.4 34.9-40.2-6.7 6.3-29.1 24.5-34.9 40.2zM248 160h136v328c0 13.3-10.7 24-24 24H24c-13.3 0-24-10.7-24-24V24C0 10.7 10.7 0 24 0h200v136c0 13.2 10.8 24 24 24zm-8 171.8c-20-12.2-33.3-29-42.7-53.8 4.5-18.5 11.6-46.6 6.2-64.2-4.7-29.4-42.4-26.5-47.8-6.8-5 18.3-.4 44.1 8.1 77-11.6 27.6-28.7 64.6-40.8 85.8-.1 0-.1.1-.2.1-27.1 13.9-73.6 44.5-54.5 68 5.6 6.9 16 10 21.5 10 17.9 0 35.7-18 61.1-61.8 25.8-8.5 54.1-19.1 79-23.2 21.7 11.8 47.1 19.5 64 19.5 29.2 0 31.2-32 19.7-43.4-13.9-13.6-54.3-9.7-73.6-7.2zM377 105L279 7c-4.5-4.5-10.6-7-17-7h-6v128h128v-6.1c0-6.3-2.5-12.4-7-16.9zm-74.1 255.3c4.1-2.7-2.5-11.9-42.8-9 37.1 15.8 42.8 9 42.8 9z\\u0022\\u003e\\u003c/path\\u003e\\u003c/svg\\u003e\"},\"type\":\"svg\"},\"localId\":\"gsbp-fc703ac\",\"styleAttributes\":{\"fill\":[\"var(\\u002d\\u002dwp\\u002d\\u002dpreset\\u002d\\u002dcolor\\u002d\\u002daccent, #de1414)\"],\"fontSize\":[\"\"],\"width\":[\"25px\"],\"height\":[\"25px\"],\"display\":[null,\"none\",\"none\",\"none\"],\"marginRight\":[\"15px\"]}} -->\n<svg viewBox=\"0 0 384 512\" xmlns=\"http://www.w3.org/2000/svg\" fill=\"currentColor\" aria-hidden=\"true\" class=\"gsbp-fc703ac\"><path d=\"M181.9 256.1c-5-16-4.9-46.9-2-46.9 8.4 0 7.6 36.9 2 46.9zm-1.7 47.2c-7.7 20.2-17.3 43.3-28.4 62.7 18.3-7 39-17.2 62.9-21.9-12.7-9.6-24.9-23.4-34.5-40.8zM86.1 428.1c0 .8 13.2-5.4 34.9-40.2-6.7 6.3-29.1 24.5-34.9 40.2zM248 160h136v328c0 13.3-10.7 24-24 24H24c-13.3 0-24-10.7-24-24V24C0 10.7 10.7 0 24 0h200v136c0 13.2 10.8 24 24 24zm-8 171.8c-20-12.2-33.3-29-42.7-53.8 4.5-18.5 11.6-46.6 6.2-64.2-4.7-29.4-42.4-26.5-47.8-6.8-5 18.3-.4 44.1 8.1 77-11.6 27.6-28.7 64.6-40.8 85.8-.1 0-.1.1-.2.1-27.1 13.9-73.6 44.5-54.5 68 5.6 6.9 16 10 21.5 10 17.9 0 35.7-18 61.1-61.8 25.8-8.5 54.1-19.1 79-23.2 21.7 11.8 47.1 19.5 64 19.5 29.2 0 31.2-32 19.7-43.4-13.9-13.6-54.3-9.7-73.6-7.2zM377 105L279 7c-4.5-4.5-10.6-7-17-7h-6v128h128v-6.1c0-6.3-2.5-12.4-7-16.9zm-74.1 255.3c4.1-2.7-2.5-11.9-42.8-9 37.1 15.8 42.8 9 42.8 9z\"></path></svg>\n<!-- /wp:greenshift-blocks/element --></div>\n<!-- /wp:greenshift-blocks/element -->\n\n<!-- wp:greenshift-blocks/element {\"id\":\"gsbp-38143f6\",\"type\":\"inner\",\"localId\":\"gsbp-38143f6\",\"styleAttributes\":{\"paddingLeft\":[null,null,\"\"]}} -->\n<div class=\"gsbp-38143f6\"><!-- wp:greenshift-blocks/dynamic-post-title {\"id\":\"gsbp-0272e1f\",\"spacing\":{\"margin\":{\"values\":{\"top\":[\"10px\"],\"bottom\":[\"15px\"]},\"locked\":false},\"padding\":{\"values\":[],\"locked\":false}},\"typography\":{\"textShadow\":[],\"size\":[\"1.2rem\"],\"line_height\":[\"1.5em\"],\"decoration\":\"remove\"}} /--></div>\n<!-- /wp:greenshift-blocks/element --></div>\n<!-- /wp:greenshift-blocks/element -->\n\n<!-- wp:greenshift-blocks/element {\"id\":\"gsbp-4f11272\",\"type\":\"inner\",\"localId\":\"gsbp-4f11272\",\"styleAttributes\":{\"width\":[\"15%\",\"20%\"],\"transformOrigin\":[null,null,\"center center\"],\"alignSelf\":[null,null,\"end\"]}} -->\n<div class=\"gsbp-4f11272\"><!-- wp:greenshift-blocks/element {\"id\":\"gsbp-950da81\",\"tag\":\"a\",\"type\":\"inner\",\"dynamiclink\":{\"dynamicEnable\":true,\"dynamicType\":\"postdata\",\"dynamicSource\":\"latest_item\",\"dynamicPostType\":\"post\",\"dynamicPostId\":0,\"dynamicPostData\":\"permalink\"},\"localId\":\"gsbp-950da81\",\"href\":\"\\u003cdynamictext\\u003e\\u003c/dynamictext\\u003e\",\"styleAttributes\":{\"display\":[\"flex\"],\"flexDirection\":[\"row\"],\"alignItems\":[\"center\"],\"columnGap\":[\"var(\\u002d\\u002dwp\\u002d\\u002dpreset\\u002d\\u002dspacing\\u002d\\u002d20, 0.44rem)\"],\"justifyContent\":[\"flex-end\"],\"textDecoration\":[\"none\"],\"width\":[null,null,\"80px\",\"80px\"],\"height\":[null,null,\"30px\",\"30px\"]}} -->\n<a class=\"gsbp-950da81\" href=\"<dynamictext&gt;</dynamictext&gt;\"><!-- wp:greenshift-blocks/element {\"id\":\"gsbp-378b59e\",\"textContent\":\"អានបន្ត\",\"tag\":\"p\",\"localId\":\"gsbp-378b59e\",\"styleAttributes\":{\"fontSize\":[\"var(\\u002d\\u002dwp\\u002d\\u002dpreset\\u002d\\u002dfont-size\\u002d\\u002ds, 1rem)\"],\"lineHeight\":[\"var(\\u002d\\u002dwp\\u002d\\u002dcustom\\u002d\\u002dline-height\\u002d\\u002ds, 1.4rem)\"],\"textDecoration\":[\"none\"],\"borderBottomLeftRadius\":[\"var(\\u002d\\u002dwp\\u002d\\u002dcustom\\u002d\\u002dborder-radius\\u002d\\u002dmini, 5px)\"],\"borderBottomRightRadius\":[\"var(\\u002d\\u002dwp\\u002d\\u002dcustom\\u002d\\u002dborder-radius\\u002d\\u002dmini, 5px)\"],\"borderTopLeftRadius\":[\"var(\\u002d\\u002dwp\\u002d\\u002dcustom\\u002d\\u002dborder-radius\\u002d\\u002dmini, 5px)\"],\"borderTopRightRadius\":[\"var(\\u002d\\u002dwp\\u002d\\u002dcustom\\u002d\\u002dborder-radius\\u002d\\u002dmini, 5px)\"],\"borderRadiusCustom_Extra\":false,\"borderRadiusLink_Extra\":true,\"paddingRight\":[\"var(\\u002d\\u002dwp\\u002d\\u002dpreset\\u002d\\u002dspacing\\u002d\\u002d30, 0.67rem)\"],\"paddingBottom\":[\"var(\\u002d\\u002dwp\\u002d\\u002dpreset\\u002d\\u002dspacing\\u002d\\u002d20, 0.44rem)\"],\"paddingLeft\":[\"var(\\u002d\\u002dwp\\u002d\\u002dpreset\\u002d\\u002dspacing\\u002d\\u002d30, 0.67rem)\"],\"paddingTop\":[\"var(\\u002d\\u002dwp\\u002d\\u002dpreset\\u002d\\u002dspacing\\u002d\\u002d20, 0.44rem)\"],\"color\":[\"#004282\"],\"color_A\":[\"var(\\u002d\\u002dwp\\u002d\\u002dpreset\\u002d\\u002dcolor\\u002d\\u002dcontrastcolor, #fffffe)\"],\"fontWeight\":[\"700\"]},\"isVariation\":\"section\"} -->\n<p class=\"gsbp-378b59e\">អានបន្ត</p>\n<!-- /wp:greenshift-blocks/element --></a>\n<!-- /wp:greenshift-blocks/element --></div>\n<!-- /wp:greenshift-blocks/element --></div>\n<!-- /wp:greenshift-blocks/element -->\n\n<!-- wp:greenshift-blocks/element {\"id\":\"gsbp-e5d4cac\",\"type\":\"inner\",\"localId\":\"gsbp-e5d4cac\",\"styleAttributes\":{\"marginLink_Extra\":\"all\",\"marginTop\":[\"0px\"],\"marginBottom\":[\"0px\"],\"marginLeft\":[\"0px\"],\"marginRight\":[\"0px\"],\"display\":[\"flex\"],\"flexDirection\":[\"row\"],\"alignItems\":[\"center\"],\"paddingLink_Extra\":\"all\",\"paddingTop\":[\"0px\"],\"paddingBottom\":[\"0px\"],\"paddingLeft\":[\"0px\"],\"paddingRight\":[\"0px\"]}} -->\n<div class=\"gsbp-e5d4cac\"><!-- wp:greenshift-blocks/element {\"id\":\"gsbp-f85f446\",\"textContent\":\"កាលបរិច្ឆេទផ្សាយ៖ \",\"tag\":\"p\",\"localId\":\"gsbp-f85f446\",\"styleAttributes\":{\"paddingTop\":[\"0px\"],\"paddingBottom\":[\"0px\"],\"paddingLeft\":[\"0px\"],\"paddingRight\":[\"15px\"],\"marginLink_Extra\":\"all\",\"marginTop\":[\"0px\"],\"marginBottom\":[\"0px\"],\"marginLeft\":[\"0px\"],\"marginRight\":[\"0px\"]}} -->\n<p class=\"gsbp-f85f446\">កាលបរិច្ឆេទផ្សាយ៖ </p>\n<!-- /wp:greenshift-blocks/element -->\n\n<!-- wp:greenshift-blocks/meta {\"id\":\"gsbp-cb5ff20\",\"selectedPostId\":0,\"post_type\":\"post\",\"type\":\"post_date\",\"typeselect\":\"postdata\",\"show_empty\":false} /--></div>\n<!-- /wp:greenshift-blocks/element --></div>\n<!-- /wp:greenshift-blocks/element -->\n<!-- /wp:greenshift-blocks/querygrid --></div>\n<!-- /wp:greenshift-blocks/element --></section>\n<!-- /wp:greenshift-blocks/element -->",
  "syncStatus": ""
}